{"TestSuite":"","Date":0,"Player":{"Development":false,"ScreenWidth":0,"ScreenHeight":0,"ScreenRefreshRate":0,"Fullscreen":false,"Vsync":0,"AntiAliasing":0,"Batchmode":false,"RenderThreadingMode":"MultiThreaded","MtRendering":false,"GraphicsJobs":false,"GpuSkinning":true,"Platform":"","ColorSpace":"","AnisotropicFiltering":"","BlendWeights":"","GraphicsApi":"","ScriptingBackend":"IL2CPP","AndroidTargetSdkVersion":"AndroidApiLevel32","AndroidBuildSystem":"Gradle","BuildTarget":"Android","StereoRenderingPath":"MultiPass"},"Hardware":{"OperatingSystem":"","DeviceModel":"","DeviceName":"","ProcessorType":"","ProcessorCount":0,"GraphicsDeviceName":"","SystemMemorySizeMB":0},"Editor":{"Version":"6000.2.15f1","Branch":"6000.2/staging","Changeset":"0707b6d1e918","Date":1764140575},"Dependencies":["com.ixxy.unitysymmetry@1.1.0","com.meta.xr.sdk.platform@69.0.0","com.sandrofigo.voxreader@5.0.6","com.unity.2d.sprite@1.0.0","com.unity.2d.tilemap@1.0.0","com.unity.cloud.draco@5.4.2","com.unity.cloud.ktx@3.6.2","com.unity.editorcoroutines@1.0.1","com.unity.formats.usd@1.0.3-preview.2","com.unity.ide.rider@3.0.38","com.unity.ide.visualstudio@2.0.25","com.unity.inputsystem@1.8.2","com.unity.localization@1.5.9","com.unity.meshopt.decompress@0.1.0-preview.7","com.unity.mobile.android-logcat@1.4.6","com.unity.multiplayer.center@1.0.0","com.unity.nuget.mono-cecil@1.11.6","com.unity.performance.profile-analyzer@1.2.4","com.unity.recorder@5.1.3","com.unity.test-framework@1.6.0","com.unity.timeline@1.8.9","com.unity.ugui@2.0.0","com.unity.vectorgraphics@2.0.0-preview.24","com.unity.xr.compositionlayers@2.2.0","com.unity.xr.core-utils@2.5.3","com.unity.xr.management@4.5.3","com.unity.xr.openxr@1.16.0","com.watertrans.glyphloader@0.0.1","com.zappar.xr.zapbox@0.3.1","dev.mikesky.openxrextensions@0.4.3","moonsharp@2.0.0","org.khronos.unitygltf@2.17.8","org.nuget.google.apis@1.64.0","org.nuget.google.apis.auth@1.64.0","org.nuget.google.apis.core@1.64.0","org.nuget.sharpziplib@1.3.1","tv.superla.radiancehdr@1.0.3","com.unity.modules.accessibility@1.0.0","com.unity.modules.ai@1.0.0","com.unity.modules.androidjni@1.0.0","com.unity.modules.animation@1.0.0","com.unity.modules.assetbundle@1.0.0","com.unity.modules.audio@1.0.0","com.unity.modules.cloth@1.0.0","com.unity.modules.director@1.0.0","com.unity.modules.imageconversion@1.0.0","com.unity.modules.imgui@1.0.0","com.unity.modules.jsonserialize@1.0.0","com.unity.modules.particlesystem@1.0.0","com.unity.modules.physics@1.0.0","com.unity.modules.physics2d@1.0.0","com.unity.modules.screencapture@1.0.0","com.unity.modules.terrain@1.0.0","com.unity.modules.terrainphysics@1.0.0","com.unity.modules.tilemap@1.0.0","com.unity.modules.ui@1.0.0","com.unity.modules.uielements@1.0.0","com.unity.modules.umbra@1.0.0","com.unity.modules.unityanalytics@1.0.0","com.unity.modules.unitywebrequest@1.0.0","com.unity.modules.unitywebrequestassetbundle@1.0.0","com.unity.modules.unitywebrequestaudio@1.0.0","com.unity.modules.unitywebrequesttexture@1.0.0","com.unity.modules.unitywebrequestwww@1.0.0","com.unity.modules.vehicles@1.0.0","com.unity.modules.video@1.0.0","com.unity.modules.wind@1.0.0","com.autodesk.fbx@4.1.0","com.unity.modules.hierarchycore@1.0.0","com.unity.nuget.newtonsoft-json@3.2.1","org.nuget.system.management@7.0.2","com.unity.shadergraph@17.2.0","com.unity.mathematics@1.3.2","com.unity.xr.legacyinputhelpers@2.1.12","com.unity.modules.xr@1.0.0","com.unity.modules.subsystems@1.0.0","com.unity.ext.nunit@2.0.5","com.unity.collections@2.6.2","com.unity.bindings.openimageio@1.0.0","com.unity.burst@1.8.25","com.unity.addressables@2.7.6","org.nuget.system.codedom@7.0.0","com.unity.render-pipelines.core@17.2.0","com.unity.searcher@4.9.3","com.unity.modules.vr@1.0.0","com.unity.test-framework.performance@3.2.0","com.unity.profiling.core@1.0.2","com.unity.scriptablebuildpipeline@2.5.0","com.unity.rendering.light-transport@1.0.1"],"Results":[]}